mantle/__init__.py
django_mantle-25.0.dist-info/LICENSE
django_mantle-25.0.dist-info/WHEEL
django_mantle-25.0.dist-info/METADATA
django_mantle-25.0.dist-info/RECORD
